circup/__init__.py
circup/backends.py
circup/bundle.py
circup/command_utils.py
circup/commands.py
circup/lazy_metadata.py
circup/logging.py
circup/module.py
circup/shared.py
circup/config/bundle_config.json
circup/config/bundle_config.json.license
circup/wwshell/README.rst
circup/wwshell/README.rst.license
circup/wwshell/__init__.py
circup/wwshell/commands.py
circup-2.3.0.dist-info/licenses/LICENSE
circup-2.3.0.dist-info/METADATA
circup-2.3.0.dist-info/WHEEL
circup-2.3.0.dist-info/entry_points.txt
circup-2.3.0.dist-info/top_level.txt
circup-2.3.0.dist-info/RECORD
