Metadata-Version: 2.4
Name: circup
Version: 2.3.0
Summary: A tool to manage/update libraries on CircuitPython devices.
Author-email: Adafruit Industries <circuitpython@adafruit.com>
License: MIT License
Project-URL: homepage, https://github.com/adafruit/circup
Keywords: adafruit,blinka,circuitpython,micropython,libraries
Classifier: Development Status :: 3 - Alpha
Classifier: Environment :: Console
Classifier: Intended Audience :: Developers
Classifier: Intended Audience :: Education
Classifier: License :: OSI Approved :: MIT License
Classifier: Operating System :: POSIX
Classifier: Operating System :: MacOS :: MacOS X
Classifier: Operating System :: Microsoft :: Windows
Classifier: Programming Language :: Python :: 3
Classifier: Programming Language :: Python :: 3.9
Classifier: Programming Language :: Python :: 3.10
Classifier: Programming Language :: Python :: 3.11
Classifier: Topic :: Education
Classifier: Topic :: Software Development :: Embedded Systems
Classifier: Topic :: System :: Software Distribution
Requires-Python: >=3.9
License-File: LICENSE
Requires-Dist: appdirs
Requires-Dist: Click
Requires-Dist: requests
Requires-Dist: semver
Requires-Dist: toml
Requires-Dist: update_checker
Provides-Extra: optional
Requires-Dist: pytest; extra == "optional"
Requires-Dist: pytest-cov; extra == "optional"
Requires-Dist: pytest-faulthandler; extra == "optional"
Requires-Dist: pytest-random-order; extra == "optional"
Dynamic: license-file
